asyncowfs/__init__.py
asyncowfs/bus.py
asyncowfs/device.py
asyncowfs/error.py
asyncowfs/event.py
asyncowfs/protocol.py
asyncowfs/server.py
asyncowfs/service.py
asyncowfs/util.py
asyncowfs/mock/__init__.py
asyncowfs/mock/server.py
asyncowfs/mock/structs.py
tests/__init__.py
tests/conftest.py
tests/test_alarm.py
tests/test_example.py
asyncowfs-0.15.2.dist-info/LICENSE
asyncowfs-0.15.2.dist-info/LICENSE.APACHE2
asyncowfs-0.15.2.dist-info/LICENSE.MIT
asyncowfs-0.15.2.dist-info/METADATA
asyncowfs-0.15.2.dist-info/WHEEL
asyncowfs-0.15.2.dist-info/top_level.txt
asyncowfs-0.15.2.dist-info/RECORD
